searchlauncher/__init__.py
searchlauncher/cli.py
searchlauncher/gui.py
searchlauncher/search.py
searchlauncher/settings/default.toml
searchlauncher/settings.py
searchlauncher/utils.py
searchlauncher-0.2.0.dist-info/entry_points.txt
searchlauncher-0.2.0.dist-info/METADATA
searchlauncher-0.2.0.dist-info/WHEEL
searchlauncher-0.2.0.dist-info/RECORD
