Metadata-Version: 2.1
Name: searchlauncher
Version: 0.2.0
Summary: Search multiple websites using a single shortcut.
Home-page: https://github.com/MikulasZelinka/searchlauncher
Author: Mikuláš Zelinka
Author-email: mikulas@zelinka.dev
Requires-Python: >=3.10,<4.0
Classifier: Programming Language :: Python :: 3
Classifier: Programming Language :: Python :: 3.10
Classifier: Programming Language :: Python :: 3.11
Requires-Dist: backports.strenum (>=1.1.1,<2.0.0) ; python_version < "3.11"
Requires-Dist: keyboard (>=0.13.5,<0.14.0)
Requires-Dist: loguru (>=0.6.0,<0.7.0)
Requires-Dist: pydantic (>=1.10.4,<2.0.0)
Requires-Dist: tomlkit (>=0.11.6,<0.12.0)
Requires-Dist: typer[all] (>=0.7.0,<0.8.0)
Project-URL: Repository, https://github.com/MikulasZelinka/searchlauncher
